ipylib/__init__.py
ipylib/datacls.py
ipylib/idatetime.py
ipylib/idebug.py
ipylib/ifile.py
ipylib/ijson.py
ipylib/ilist.py
ipylib/imath.py
ipylib/inumber.py
ipylib/iparser.py
ipylib/ipath.py
ipylib/syspath.py
ipylib-0.3.1.dist-info/LICENSE
ipylib-0.3.1.dist-info/METADATA
ipylib-0.3.1.dist-info/WHEEL
ipylib-0.3.1.dist-info/top_level.txt
ipylib-0.3.1.dist-info/RECORD
