Metadata-Version: 2.1
Name: ipylib
Version: 0.3.1
Summary: Pure Python3 기능을 재사용하기 위해 한단계 추상화된 라이브러리 패키지
Home-page: https://github.com/innovata/iPyLibrary
Author: innovata
Author-email: iinnovata@gmail.com
Classifier: Programming Language :: Python :: 3
Classifier: License :: OSI Approved :: MIT License
Classifier: Operating System :: OS Independent
Requires-Python: >=3.8
License-File: LICENSE
